<?xml version="1.0" encoding="utf-8"?>
<facturaComputarizadaCompraVenta xmlns:xsi="http://www.w3.org/2001/XMLSchema-instance" xsi:noNamespaceSchemaLocation="facturaComputarizadaCompraVenta.xsd">
    <cabecera>
        <nitEmisor>8688070018</nitEmisor>
        <razonSocialEmisor>PASSWORD</razonSocialEmisor>
        <municipio>CERCADO - COCHABAMBA</municipio>
        <telefono>4511518 * (591) 79999097</telefono>
        <numeroFactura>141</numeroFactura>
        <cuf>252763D5BB64BBA5ABA04BBA5D7A504274F55BFA6250C77D488E4A6D74</cuf>
        <cufd>BQT5CwqE+P0lBNzzlFRkRBNjUwMTc=Q1VWNkVMY0hXVUFIxOThFQUVGQjZBM</cufd>
        <codigoSucursal>0</codigoSucursal>
        <direccion>URUGUAY Nº 454, ENTRE SAN MARTIN Y 25 DE MAYO</direccion>
        <codigoPuntoVenta>0</codigoPuntoVenta>
        <fechaEmision>2022-07-27T12:17:07.504</fechaEmision>
        <nombreRazonSocial>SIN NOMBRE</nombreRazonSocial>
        <codigoTipoDocumentoIdentidad>5</codigoTipoDocumentoIdentidad>
        <numeroDocumento>0</numeroDocumento>
        <complemento></complemento>
        <codigoCliente></codigoCliente>
        <codigoMetodoPago>1</codigoMetodoPago>
        <numeroTarjeta>0</numeroTarjeta>
        <montoTotal>170.00</montoTotal>
        <montoTotalSujetoIva>170.00</montoTotalSujetoIva>
        <codigoMoneda>1</codigoMoneda>
        <tipoCambio>1</tipoCambio>
        <montoTotalMoneda>170.00</montoTotalMoneda>
        <montoGiftCard>0.000</montoGiftCard>        
        <descuentoAdicional>0.00</descuentoAdicional>
        <codigoExcepcion>0</codigoExcepcion>  
        <cafc xsi:nil="true"/>
        <leyenda>ESTA FACTURA CONTRIBUYE AL DESARROLLO DEL PAIS, EL USO ILICITO DE ESTÁ SERÁ SANCINADO DE ACUERDO A LEY</leyenda>
        <usuario>LIDIA CALA CALDERON</usuario>
        <codigoDocumentoSector>1</codigoDocumentoSector>
    </cabecera>
    
<detalle><actividadEconomica>472000</actividadEconomica><codigoProductoSin>99100</codigoProductoSin><codigoProducto>TEC-00148</codigoProducto><descripcion>TECLADO FLEXIBLE KEYBOARD</descripcion><cantidad>2</cantidad><unidadMedida>47</unidadMedida><precioUnitario>85.00</precioUnitario><montoDescuento>0</montoDescuento><subTotal>170.00</subTotal><numeroSerie/><numeroImei/></detalle></facturaComputarizadaCompraVenta>
